CHANGELOG.md
LICENSE
README.md
xiaoai/__init__.py
xiaoai/exceptions.py
xiaoai/utils.py
xiaoai-0.1.0.dist-info/LICENSE
xiaoai-0.1.0.dist-info/WHEEL
xiaoai-0.1.0.dist-info/METADATA
xiaoai-0.1.0.dist-info/RECORD
